Metadata-Version: 1.0
Name: fldataparser
Version: 0.0.2
Summary: parser tool for object send through rabbitmq in FLExplorer
Home-page: UNKNOWN
Author: UNKNOWN
Author-email: UNKNOWN
License: UNKNOWN
Platform: UNKNOWN
